pytoutv-3.0.0.dist-info/DESCRIPTION.rst
pytoutv-3.0.0.dist-info/METADATA
pytoutv-3.0.0.dist-info/RECORD
pytoutv-3.0.0.dist-info/WHEEL
pytoutv-3.0.0.dist-info/entry_points.txt
pytoutv-3.0.0.dist-info/metadata.json
pytoutv-3.0.0.dist-info/top_level.txt
toutv/__init__.py
toutv/auth.py
toutv/bos.py
toutv/cache.py
toutv/client.py
toutv/config.py
toutv/dl.py
toutv/exceptions.py
toutv/m3u8.py
toutv/mapper.py
toutv/transport.py
toutvcli/__init__.py
toutvcli/app.py
toutvcli/progressbar.py
toutvqt/__init__.py
toutvqt/about_dialog.py
toutvqt/app.py
toutvqt/choose_bitrate_dialog.py
toutvqt/config.py
toutvqt/download_manager.py
toutvqt/downloads_itemdelegate.py
toutvqt/downloads_tablemodel.py
toutvqt/downloads_tableview.py
toutvqt/emissions_treemodel.py
toutvqt/emissions_treeview.py
toutvqt/infos_frame.py
toutvqt/main_window.py
toutvqt/preferences_dialog.py
toutvqt/settings.py
toutvqt/utils.py
toutvqt/dat/icons/about_action.png
toutvqt/dat/icons/cancel_action.png
toutvqt/dat/icons/open_action.png
toutvqt/dat/icons/open_dir_action.png
toutvqt/dat/icons/preferences_action.png
toutvqt/dat/icons/quit_action.png
toutvqt/dat/icons/refresh_emissions_action.png
toutvqt/dat/icons/remove_item_action.png
toutvqt/dat/icons/toutv.png
toutvqt/dat/ui/about_dialog.ui
toutvqt/dat/ui/choose_bitrate_dialog.ui
toutvqt/dat/ui/emission_infos_widget.ui
toutvqt/dat/ui/episode_infos_widget.ui
toutvqt/dat/ui/main_window.ui
toutvqt/dat/ui/preferences_dialog.ui
toutvqt/dat/ui/season_infos_widget.ui
