Metadata-Version: 2.0
Name: pytoutv
Version: 3.0.0
Summary: TOU.TV client library and user interfaces
Home-page: https://github.com/bvanheu/pytoutv
Author: Benjamin Vanheuverzwijn
Author-email: bvanheu@gmail.com
License: BSD
Keywords: TOUTV
Platform: UNKNOWN
Requires-Dist: pycrypto (>=2.0.0)
Requires-Dist: requests (>=2.0.0)
Requires-Dist: setuptools (>=3.0)
